dsbox/__init__.py
dsbox/datapreprocessing/__init__.py
dsbox/datapreprocessing/cleaner/Iterative_regress.py
dsbox/datapreprocessing/cleaner/__init__.py
dsbox/datapreprocessing/cleaner/discretizer.py
dsbox/datapreprocessing/cleaner/encoder.py
dsbox/datapreprocessing/cleaner/greedy.py
dsbox/datapreprocessing/cleaner/knn.py
dsbox/datapreprocessing/cleaner/mean.py
dsbox/datapreprocessing/cleaner/mice.py
dsbox/datapreprocessing/cleaner/missing_value_pred.py
dsbox/datapreprocessing/cleaner/unary_encoder.py
dsbox_datacleaning-0.3.1.post4.dist-info/DESCRIPTION.rst
dsbox_datacleaning-0.3.1.post4.dist-info/METADATA
dsbox_datacleaning-0.3.1.post4.dist-info/RECORD
dsbox_datacleaning-0.3.1.post4.dist-info/WHEEL
dsbox_datacleaning-0.3.1.post4.dist-info/entry_points.txt
dsbox_datacleaning-0.3.1.post4.dist-info/metadata.json
dsbox_datacleaning-0.3.1.post4.dist-info/top_level.txt
