Metadata-Version: 2.0
Name: dsbox-datacleaning
Version: 0.3.1.post4
Summary: DSBox data preprocessing tools for cleaning data
Home-page: https://github.com/usc-isi-i2/dsbox-cleaning.git
Author: Ke-Thia Yao
Author-email: kyao@isi.edu
License: MIT
Keywords: d3m_primitive
Platform: UNKNOWN
Requires-Python: >=3.6
Requires-Dist: scipy (>=0.19.0)
Requires-Dist: numpy (>=1.11.1)
Requires-Dist: pandas (>=0.20.1)
Requires-Dist: langdetect (>=1.0.7)
Requires-Dist: scikit-learn (>=0.18.0)
Requires-Dist: python-dateutil (>=2.5.2)
Requires-Dist: six (>=1.10.0)
Requires-Dist: keras (>=2.1)
Requires-Dist: tensorflow (>=1.4)
Requires-Dist: fancyimpute
Requires-Dist: stopit
